datasets_sql/__init__.py
datasets_sql/query.py
datasets_sql-0.4.0.dist-info/LICENSE
datasets_sql-0.4.0.dist-info/METADATA
datasets_sql-0.4.0.dist-info/WHEEL
datasets_sql-0.4.0.dist-info/top_level.txt
datasets_sql-0.4.0.dist-info/RECORD
