Metadata-Version: 2.1
Name: datasets-sql
Version: 0.4.0
Summary: datasets_sql is an extension package of 🤗 Datasets package that provides support for executing arbitrary SQL queries on datasets.
Home-page: https://github.com/mariosasko/datasets_sql
Author: Mario Šaško
Author-email: mariosasko777@gmail.com
License: Apache
Keywords: datasets
Requires-Python: >=3.7.0
License-File: LICENSE
Requires-Dist: pyarrow >=5.0.0
Requires-Dist: datasets
Requires-Dist: duckdb >=0.4.0
Provides-Extra: dev
Requires-Dist: pytest ; extra == 'dev'
Requires-Dist: numpy ; extra == 'dev'
Requires-Dist: black ~=22.0 ; extra == 'dev'
Requires-Dist: flake8 >=3.8.3 ; extra == 'dev'
Requires-Dist: isort >=5.0.0 ; extra == 'dev'
Provides-Extra: tests
Requires-Dist: pytest ; extra == 'tests'
Requires-Dist: numpy ; extra == 'tests'
